{"is_source_file": false, "format": "", "description": "", "external_files": [], "external_methods": [], "published": [], "classes": [], "methods": [], "calls": [], "search-terms": [], "state": 2, "file_id": 17, "knowledge_revision": 48, "git_revision": "dadd6195e96eb6c4b23eb7332cbc7c0f8d1f4a61", "revision_history": [{"45": "4a19785bbd9cd4444120a90737abfba6b5201ac7"}, {"48": "dadd6195e96eb6c4b23eb7332cbc7c0f8d1f4a61"}], "hash": "f0a414c2a10f3e505e222357e56306fb", "format-version": 4, "code-base-name": "react_frontend", "filename": "assets/supabase.md"}