{"is_source_file": true, "format": "JavaScript", "description": "This is the main entry point for a React application, responsible for rendering the root component into the DOM.", "external_files": ["react", "react-dom/client", "./index.css", "./App"], "external_methods": ["ReactDOM.createRoot", "root.render"], "published": [], "classes": [], "methods": [{"name": "root.render", "description": "Renders the React application into the DOM element with id 'root', wrapped in React.StrictMode."}], "calls": ["ReactDOM.createRoot", "root.render"], "search-terms": ["React", "ReactDOM", "render", "index.js", "main entry point", "React.StrictMode"], "state": 2, "file_id": 5, "knowledge_revision": 24, "git_revision": "0cb109c17c0b848d720391bfaad244601a788260", "ctags": [{"_type": "tag", "name": "root", "path": "/home/kavia/workspace/code-generation/taskmate-real-time-database-integration-20766-20775/react_frontend/src/index.js", "pattern": "/^const root = ReactDOM.createRoot(document.getElementById('root'));$/", "language": "JavaScript", "kind": "constant"}], "hash": "9fc5841375336fc175b49f8767a11383", "format-version": 4, "code-base-name": "react_frontend", "filename": "react_frontend/src/index.js", "revision_history": [{"24": "0cb109c17c0b848d720391bfaad244601a788260"}]}